<annotation>
	<folder></folder>
	<filename>0405_05175_b_jpg.rf.2df90e2821ea4532c4a078c5acead185.jpg</filename>
	<path>0405_05175_b_jpg.rf.2df90e2821ea4532c4a078c5acead185.jpg</path>
	<source>
		<database>roboflow.com</database>
	</source>
	<size>
		<width>640</width>
		<height>640</height>
		<depth>3</depth>
	</size>
	<segmented>0</segmented>
	<object>
		<name>license_plate</name>
		<pose>Unspecified</pose>
		<truncated>0</truncated>
		<difficult>0</difficult>
		<occluded>0</occluded>
		<bndbox>
			<xmin>215</xmin>
			<xmax>327</xmax>
			<ymin>232</ymin>
			<ymax>374</ymax>
		</bndbox>
		<polygon>
			<x1>219.20904</x1>
			<y1>373.157316</y1>
			<x2>326.327684</x2>
			<y2>368.228822</y2>
			<x3>320.451977</x3>
			<y3>230.935093</y3>
			<x4>214.237288</x4>
			<y4>237.975798</y4>
			<x5>219.20904</x5>
			<y5>373.157316</y5>
		</polygon>
	</object>
	<metadata>
	</metadata>
</annotation>
