<annotation>
	<folder></folder>
	<filename>0430_05970_b_jpg.rf.418b07b0ae2080dd72494c222357ca12.jpg</filename>
	<path>0430_05970_b_jpg.rf.418b07b0ae2080dd72494c222357ca12.jpg</path>
	<source>
		<database>roboflow.com</database>
	</source>
	<size>
		<width>640</width>
		<height>640</height>
		<depth>3</depth>
	</size>
	<segmented>0</segmented>
	<object>
		<name>license_plate</name>
		<pose>Unspecified</pose>
		<truncated>0</truncated>
		<difficult>0</difficult>
		<occluded>0</occluded>
		<bndbox>
			<xmin>291</xmin>
			<xmax>392</xmax>
			<ymin>294</ymin>
			<ymax>441</ymax>
		</bndbox>
		<polygon>
			<x1>387.825292</x1>
			<y1>440.187294</y1>
			<x2>391.370797</x2>
			<y2>302.048558</y2>
			<x3>290.417639</x3>
			<y3>293.36267</y3>
			<x4>291.387904</x4>
			<y4>433.556657</y4>
			<x5>387.825292</x5>
			<y5>440.187294</y5>
		</polygon>
	</object>
	<metadata>
	</metadata>
</annotation>
