<annotation>
	<folder></folder>
	<filename>Dieu_0110_png.rf.32130b6dd699bc1e63a697d9a4b4de38.jpg</filename>
	<path>Dieu_0110_png.rf.32130b6dd699bc1e63a697d9a4b4de38.jpg</path>
	<source>
		<database>roboflow.com</database>
	</source>
	<size>
		<width>640</width>
		<height>640</height>
		<depth>3</depth>
	</size>
	<segmented>0</segmented>
	<object>
		<name>license_plate</name>
		<pose>Unspecified</pose>
		<truncated>0</truncated>
		<difficult>0</difficult>
		<occluded>0</occluded>
		<bndbox>
			<xmin>149</xmin>
			<xmax>208</xmax>
			<ymin>326</ymin>
			<ymax>389</ymax>
		</bndbox>
		<polygon>
			<x1>151.072107</x1>
			<y1>387.973845</y1>
			<x2>207.182178</x2>
			<y2>386.549424</y2>
			<x3>205.044643</x3>
			<y3>326.726269</y3>
			<x4>148.449131</x4>
			<y4>325.314294</y4>
			<x5>151.072107</x5>
			<y5>387.973845</y5>
		</polygon>
	</object>
	<metadata>
	</metadata>
</annotation>
