<annotation>
	<folder></folder>
	<filename>Dieu_0123_png.rf.1b0fc35ef7a172e86da3fea7519bfbf5.jpg</filename>
	<path>Dieu_0123_png.rf.1b0fc35ef7a172e86da3fea7519bfbf5.jpg</path>
	<source>
		<database>roboflow.com</database>
	</source>
	<size>
		<width>640</width>
		<height>640</height>
		<depth>3</depth>
	</size>
	<segmented>0</segmented>
	<object>
		<name>license_plate</name>
		<pose>Unspecified</pose>
		<truncated>0</truncated>
		<difficult>0</difficult>
		<occluded>0</occluded>
		<bndbox>
			<xmin>249</xmin>
			<xmax>347</xmax>
			<ymin>441</ymin>
			<ymax>489</ymax>
		</bndbox>
		<polygon>
			<x1>248.425071</x1>
			<y1>479.238095</y1>
			<x2>332.930322</x2>
			<y2>487.619047</y2>
			<x3>346.166084</x3>
			<y3>442.666667</y3>
			<x4>258.606426</x4>
			<y4>440.380953</y4>
			<x5>248.425071</x5>
			<y5>479.238095</y5>
		</polygon>
	</object>
	<metadata>
	</metadata>
</annotation>
