<annotation>
	<folder></folder>
	<filename>Hung_0173_png.rf.14c248690bdbbbca027cdf71f9f41732.jpg</filename>
	<path>Hung_0173_png.rf.14c248690bdbbbca027cdf71f9f41732.jpg</path>
	<source>
		<database>roboflow.com</database>
	</source>
	<size>
		<width>640</width>
		<height>640</height>
		<depth>3</depth>
	</size>
	<segmented>0</segmented>
	<object>
		<name>license_plate</name>
		<pose>Unspecified</pose>
		<truncated>0</truncated>
		<difficult>0</difficult>
		<occluded>0</occluded>
		<bndbox>
			<xmin>5</xmin>
			<xmax>70</xmax>
			<ymin>174</ymin>
			<ymax>276</ymax>
		</bndbox>
		<polygon>
			<x1>8.264985</x1>
			<y1>275.370197</y1>
			<x2>68.84158</x2>
			<y2>271.959012</y2>
			<x3>63.722443</x3>
			<y3>173.034362</y3>
			<x4>4.479981</x4>
			<y4>182.32889</y4>
			<x5>8.264985</x5>
			<y5>275.370197</y5>
		</polygon>
	</object>
	<object>
		<name>license_plate</name>
		<pose>Unspecified</pose>
		<truncated>0</truncated>
		<difficult>0</difficult>
		<occluded>0</occluded>
		<bndbox>
			<xmin>188</xmin>
			<xmax>279</xmax>
			<ymin>164</ymin>
			<ymax>272</ymax>
		</bndbox>
		<polygon>
			<x1>186.581993</x1>
			<y1>268.547826</y1>
			<x2>259.956528</x2>
			<y2>270.821921</y2>
			<x3>277.87354</x3>
			<y3>162.800761</y3>
			<x4>201.813314</x4>
			<y4>165.262224</y4>
			<x5>186.581993</x5>
			<y5>268.547826</y5>
		</polygon>
	</object>
	<object>
		<name>license_plate</name>
		<pose>Unspecified</pose>
		<truncated>0</truncated>
		<difficult>0</difficult>
		<occluded>0</occluded>
		<bndbox>
			<xmin>486</xmin>
			<xmax>627</xmax>
			<ymin>345</ymin>
			<ymax>523</ymax>
		</bndbox>
		<polygon>
			<x1>485.199142</x1>
			<y1>468.671307</y1>
			<x2>606.352334</x2>
			<y2>522.113277</y2>
			<x3>625.975769</x3>
			<y3>386.802543</y3>
			<x4>503.679981</x4>
			<y4>344.462224</y4>
			<x5>485.199142</x5>
			<y5>468.671307</y5>
		</polygon>
	</object>
	<metadata>
	</metadata>
</annotation>
