<annotation>
	<folder></folder>
	<filename>z5295323133977_8284d64c9cdf065a0d0db3712b9aac42_jpg.rf.2aad5d2408f8eb16ed607c4269498880.jpg</filename>
	<path>z5295323133977_8284d64c9cdf065a0d0db3712b9aac42_jpg.rf.2aad5d2408f8eb16ed607c4269498880.jpg</path>
	<source>
		<database>roboflow.com</database>
	</source>
	<size>
		<width>640</width>
		<height>640</height>
		<depth>3</depth>
	</size>
	<segmented>0</segmented>
	<object>
		<name>license_plate</name>
		<pose>Unspecified</pose>
		<truncated>0</truncated>
		<difficult>0</difficult>
		<occluded>0</occluded>
		<bndbox>
			<xmin>518</xmin>
			<xmax>594</xmax>
			<ymin>377</ymin>
			<ymax>401</ymax>
		</bndbox>
		<polygon>
			<x1>591.300287</x1>
			<y1>400.350838</y1>
			<x2>593.439435</x2>
			<y2>381.51775</y2>
			<x3>518.818588</x3>
			<y3>376.071736</y3>
			<x4>517.285948</x4>
			<y4>396.355992</y4>
			<x5>591.300287</x5>
			<y5>400.350838</y5>
		</polygon>
	</object>
	<object>
		<name>license_plate</name>
		<pose>Unspecified</pose>
		<truncated>0</truncated>
		<difficult>0</difficult>
		<occluded>0</occluded>
		<bndbox>
			<xmin>173</xmin>
			<xmax>266</xmax>
			<ymin>387</ymin>
			<ymax>413</ymax>
		</bndbox>
		<polygon>
			<x1>263.583721</x1>
			<y1>411.764834</y1>
			<x2>264.867246</x2>
			<y2>387.795485</y2>
			<x3>173.295997</x3>
			<y3>385.69632</y3>
			<x4>172.028441</x4>
			<y4>410.623478</y4>
			<x5>263.583721</x5>
			<y5>411.764834</y5>
		</polygon>
	</object>
	<metadata>
	</metadata>
</annotation>
