<annotation>
	<folder></folder>
	<filename>z5297743324969_1378bfc1693780260e44b8b9b67667c3_jpg.rf.1b36224859c14a59ee2793600e879ea4.jpg</filename>
	<path>z5297743324969_1378bfc1693780260e44b8b9b67667c3_jpg.rf.1b36224859c14a59ee2793600e879ea4.jpg</path>
	<source>
		<database>roboflow.com</database>
	</source>
	<size>
		<width>640</width>
		<height>640</height>
		<depth>3</depth>
	</size>
	<segmented>0</segmented>
	<object>
		<name>license_plate</name>
		<pose>Unspecified</pose>
		<truncated>0</truncated>
		<difficult>0</difficult>
		<occluded>0</occluded>
		<bndbox>
			<xmin>253</xmin>
			<xmax>334</xmax>
			<ymin>191</ymin>
			<ymax>297</ymax>
		</bndbox>
		<polygon>
			<x1>330.361473</x1>
			<y1>295.686962</y1>
			<x2>333.390236</x2>
			<y2>196.562349</y2>
			<x3>253.853318</x3>
			<y3>190.460532</y3>
			<x4>251.614026</x4>
			<y4>294.506869</y4>
			<x5>330.361473</x5>
			<y5>295.686962</y5>
		</polygon>
	</object>
	<metadata>
	</metadata>
</annotation>
