<annotation>
	<folder></folder>
	<filename>z5325425430834_d1c8a1bd015020a6cab322b02bdf1111_jpg.rf.db147c9c42edc5056a6c95d2e2c7de8b.jpg</filename>
	<path>z5325425430834_d1c8a1bd015020a6cab322b02bdf1111_jpg.rf.db147c9c42edc5056a6c95d2e2c7de8b.jpg</path>
	<source>
		<database>roboflow.com</database>
	</source>
	<size>
		<width>640</width>
		<height>640</height>
		<depth>3</depth>
	</size>
	<segmented>0</segmented>
	<object>
		<name>license_plate</name>
		<pose>Unspecified</pose>
		<truncated>0</truncated>
		<difficult>0</difficult>
		<occluded>0</occluded>
		<bndbox>
			<xmin>142</xmin>
			<xmax>196</xmax>
			<ymin>289</ymin>
			<ymax>318</ymax>
		</bndbox>
		<polygon>
			<x1>141.481102</x1>
			<y1>308.598097</y1>
			<x2>195.171367</x2>
			<y2>317.304626</y2>
			<x3>195.026258</x3>
			<y3>296.215477</y3>
			<x4>140.755558</x4>
			<y4>287.895905</y4>
			<x5>141.481102</x5>
			<y5>308.598097</y5>
		</polygon>
	</object>
	<object>
		<name>license_plate</name>
		<pose>Unspecified</pose>
		<truncated>0</truncated>
		<difficult>0</difficult>
		<occluded>0</occluded>
		<bndbox>
			<xmin>414</xmin>
			<xmax>478</xmax>
			<ymin>332</ymin>
			<ymax>360</ymax>
		</bndbox>
		<polygon>
			<x1>413.415036</x1>
			<y1>350.389438</y1>
			<x2>475.376504</x2>
			<y2>358.515532</y2>
			<x3>476.972701</x3>
			<y3>338.587253</y3>
			<x4>413.850363</x4>
			<y4>331.235073</y4>
			<x5>413.415036</x5>
			<y5>350.389438</y5>
		</polygon>
	</object>
	<metadata>
	</metadata>
</annotation>
