<annotation>
	<folder></folder>
	<filename>z5325394253853_d30107029e0553590b81d684d846982c_jpg.rf.c13b218372f13cd7407423f48409e24f.jpg</filename>
	<path>z5325394253853_d30107029e0553590b81d684d846982c_jpg.rf.c13b218372f13cd7407423f48409e24f.jpg</path>
	<source>
		<database>roboflow.com</database>
	</source>
	<size>
		<width>640</width>
		<height>640</height>
		<depth>3</depth>
	</size>
	<segmented>0</segmented>
	<object>
		<name>license_plate</name>
		<pose>Unspecified</pose>
		<truncated>0</truncated>
		<difficult>0</difficult>
		<occluded>0</occluded>
		<bndbox>
			<xmin>185</xmin>
			<xmax>448</xmax>
			<ymin>250</ymin>
			<ymax>302</ymax>
		</bndbox>
		<polygon>
			<x1>184.166667</x1>
			<y1>294.375</y1>
			<x2>444.166667</x2>
			<y2>300.625</y2>
			<x3>446.666667</x3>
			<y3>253.75</y3>
			<x4>185</x4>
			<y4>248.75</y4>
			<x5>184.166667</x5>
			<y5>294.375</y5>
		</polygon>
	</object>
	<metadata>
	</metadata>
</annotation>
