<annotation>
	<folder></folder>
	<filename>z5325448425011_e420302b15866f24de44b9db9e8522c2_jpg.rf.57e7d19e973057686b1ed6258ce175d5.jpg</filename>
	<path>z5325448425011_e420302b15866f24de44b9db9e8522c2_jpg.rf.57e7d19e973057686b1ed6258ce175d5.jpg</path>
	<source>
		<database>roboflow.com</database>
	</source>
	<size>
		<width>640</width>
		<height>640</height>
		<depth>3</depth>
	</size>
	<segmented>0</segmented>
	<object>
		<name>license_plate</name>
		<pose>Unspecified</pose>
		<truncated>0</truncated>
		<difficult>0</difficult>
		<occluded>0</occluded>
		<bndbox>
			<xmin>282</xmin>
			<xmax>446</xmax>
			<ymin>363</ymin>
			<ymax>397</ymax>
		</bndbox>
		<polygon>
			<x1>440.019362</x1>
			<y1>362.435327</y1>
			<x2>281.738222</x2>
			<y2>361.501349</y2>
			<x3>281.322808</x3>
			<y3>394.812911</y3>
			<x4>444.987725</x4>
			<y4>395.840262</y4>
			<x5>440.019362</x5>
			<y5>362.435327</y5>
		</polygon>
	</object>
	<metadata>
	</metadata>
</annotation>
